{
  "semi": true,
  "singleQuote": false,
  "tabWidth": 2,
  "trailingComma": "es5",
  "tailwindFunctions": ["cn"],
  "importOrder": [
    "^(react|next?/?([a-zA-z/]*))$",
    "<THIRD_PARTY_MODULES>",
    "^@/lib/(.*)$",
    "^@/components/(.*)$",
    "^@/(.*)$",
    "^[./]"
  ],
  "importOrderSeparation": true,
  "importOrderSortSpecifiers": true,
  "importOrderCaseInsensitive": true,
  "importOrderGroupNamespaceSpecifiers": true,
  "plugins": ["@trivago/prettier-plugin-sort-imports", "prettier-plugin-tailwindcss"]
}
